ws_sheets/__init__.py
ws_sheets/cell.py
ws_sheets/cells.py
ws_sheets/context.py
ws_sheets/exception.py
ws_sheets/helper.py
ws_sheets/middleware.py
ws_sheets/script.py
ws_sheets/test.py
ws_sheets/version.py
ws_sheets/ext/middleware/__init__.py
ws_sheets/ext/middleware/security.py
ws_sheets/tests/__init__.py
ws_sheets/tests/builtin_open.py
ws_sheets/tests/function_attributes.py
ws_sheets/tests/functions.py
ws_sheets/tests/getitem.py
ws_sheets/tests/script_post.py
ws_sheets/tests/script_pre_security.py
ws_sheets/tests/security.py
ws_sheets/tests/set_cell.py
ws_sheets/tests/set_script_pre.py
ws_sheets/tests/conf/__init__.py
ws_sheets/tests/conf/simple.py
ws_sheets-0.4.2.dist-info/DESCRIPTION.rst
ws_sheets-0.4.2.dist-info/METADATA
ws_sheets-0.4.2.dist-info/RECORD
ws_sheets-0.4.2.dist-info/WHEEL
ws_sheets-0.4.2.dist-info/metadata.json
ws_sheets-0.4.2.dist-info/top_level.txt
