Metadata-Version: 2.0
Name: ws-sheets
Version: 0.4.2
Summary: python spreadsheets
Home-page: http://github.com/chuck1/ws_sheets
Author: Charles Rymal
Author-email: charlesrymal@gmail.com
License: MIT
Platform: UNKNOWN
